xiguapi_mcp_douyindl/__init__.py
xiguapi_mcp_douyindl-0.4.0.dist-info/METADATA
xiguapi_mcp_douyindl-0.4.0.dist-info/WHEEL
xiguapi_mcp_douyindl-0.4.0.dist-info/entry_points.txt
xiguapi_mcp_douyindl-0.4.0.dist-info/RECORD
