Metadata-Version: 2.4
Name: xiguapi-mcp-douyindl
Version: 0.4.0
Summary: get douyin video download url
Requires-Python: >=3.13
Requires-Dist: drissionpage==4.1.0.18
Requires-Dist: mcp[cli]>=1.9.3
